rsttst/__init__.py
rsttst/__main__.py
rsttst/core.py
rsttst/rsttst.py
rsttst-0.3.0.dist-info/DESCRIPTION.rst
rsttst-0.3.0.dist-info/entry_points.txt
rsttst-0.3.0.dist-info/METADATA
rsttst-0.3.0.dist-info/metadata.json
rsttst-0.3.0.dist-info/RECORD
rsttst-0.3.0.dist-info/top_level.txt
rsttst-0.3.0.dist-info/WHEEL
