Metadata-Version: 2.0
Name: rsttst
Version: 0.3.0
Summary: rsttst makes your reStructuredText testable
Home-page: https://github.com/willemt/rsttst
Author: willemt
Author-email: himself@willemthiart.com
License: BSD
Keywords: development logging
Platform: UNKNOWN
Classifier: Development Status :: 3 - Alpha
Classifier: Intended Audience :: Developers
Classifier: Topic :: System :: Logging
Classifier: License :: OSI Approved :: BSD License
Classifier: Programming Language :: Python :: 2.6
Classifier: Programming Language :: Python :: 2.7
Classifier: Programming Language :: Python :: 3
Classifier: Programming Language :: Python :: 3.2
Classifier: Programming Language :: Python :: 3.3
Classifier: Programming Language :: Python :: 3.4
Requires-Dist: pygments
Requires-Dist: docutils
